setup.py
django_globetrotter.egg-info/PKG-INFO
django_globetrotter.egg-info/SOURCES.txt
django_globetrotter.egg-info/dependency_links.txt
django_globetrotter.egg-info/not-zip-safe
django_globetrotter.egg-info/requires.txt
django_globetrotter.egg-info/top_level.txt
globetrotter/__init__.py
globetrotter/fields.py
globetrotter/middleware.py
globetrotter/models.py
globetrotter/tests.py
globetrotter/utils.py
globetrotter/views.py