Metadata-Version: 1.0
Name: django-globetrotter
Version: 0.0.5
Summary: Extra i18n + l10n tools for Django
Home-page: https://github.com/jarcoal/django-globetrotter
Author: Jared Morse <jarcoal@gmail.com>
Author-email: jarcoal@gmail.com
License: BSD
Keywords: django,i18n,l10n
Platform: UNKNOWN
Classifier: Programming Language :: Python
Classifier: Topic :: Software Development :: Libraries :: Python Modules
Classifier: Framework :: Django
Classifier: Environment :: Web Environment
